{"network": {"name": "WideJpn", "routers": [{"interfaces": [{"names": ["i0", "i1", "i2", "i3", "i4", "i5", "i6", "i7"], "routing_table": {}}], "location": {"latitude": 0.0, "longitude": 0.0}, "name": "a0_KDDI_Otemachi"}, {"interfaces": [{"names": ["i0", "i1", "i2"], "routing_table": {}}], "location": {"latitude": 0.0, "longitude": 0.0}, "name": "a1_Nezu"}, {"interfaces": [{"names": ["i0", "i1", "i2"], "routing_table": {}}], "location": {"latitude": 0.0, "longitude": 0.0}, "name": "a2_Yagami"}, {"interfaces": [{"names": ["i0", "i1", "i2", "i3", "i4", "i5", "i6"], "routing_table": {}}], "location": {"latitude": 0.0, "longitude": 0.0}, "name": "a6_NTT_Otemachi"}, {"interfaces": [{"names": ["i0", "i1", "i2", "i3", "i4", "i5", "i6", "i7"], "routing_table": {}}], "location": {"latitude": 0.0, "longitude": 0.0}, "name": "a10_Dojima"}, {"interfaces": [{"names": ["i0", "i1", "i2"], "routing_table": {}}], "location": {"latitude": 0.0, "longitude": 0.0}, "name": "a21_Fujisawa"}, {"interfaces": [{"names": ["i0", "i1", "i2"], "routing_table": {}}], "location": {"latitude": 0.0, "longitude": 0.0}, "name": "a22_Nara"}, {"interfaces": [{"names": ["i0", "i1", "i2"], "routing_table": {}}], "location": {"latitude": 0.0, "longitude": 0.0}, "name": "a23_Fukuoka"}, {"interfaces": [{"names": ["i0", "i1"], "routing_table": {}}], "location": {"latitude": 0.0, "longitude": 0.0}, "name": "a24_Hiroshima"}, {"interfaces": [{"names": ["i0", "i1"], "routing_table": {}}], "location": {"latitude": 0.0, "longitude": 0.0}, "name": "a25_Kurashiki"}, {"interfaces": [{"names": ["i0", "i1"], "routing_table": {}}], "location": {"latitude": 0.0, "longitude": 0.0}, "name": "a26_Sakyo"}], "links": [{"bandwidth": 888252, "from_router": "a0_KDDI_Otemachi", "to_router": "a1_Nezu", "latency": 11, "weight": 10, "from_interface": "i0", "to_interface": "i0", "bidirectional": true}, {"bandwidth": 888252, "from_router": "a0_KDDI_Otemachi", "to_router": "a6_NTT_Otemachi", "latency": 5, "weight": 10, "from_interface": "i2", "to_interface": "i0", "bidirectional": true}, {"bandwidth": 888252, "from_router": "a1_Nezu", "to_router": "a2_Yagami", "latency": 1603, "weight": 10, "from_interface": "i1", "to_interface": "i0", "bidirectional": true}, {"bandwidth": 888252, "from_router": "a2_Yagami", "to_router": "a21_Fujisawa", "latency": 1540, "weight": 10, "from_interface": "i2", "to_interface": "i0", "bidirectional": true}, {"bandwidth": 888252, "from_router": "a6_NTT_Otemachi", "to_router": "a10_Dojima", "latency": 679, "weight": 10, "from_interface": "i3", "to_interface": "i0", "bidirectional": true}, {"bandwidth": 888252, "from_router": "a10_Dojima", "to_router": "a22_Nara", "latency": 53, "weight": 10, "from_interface": "i3", "to_interface": "i0", "bidirectional": true}, {"bandwidth": 888252, "from_router": "a10_Dojima", "to_router": "a23_Fukuoka", "latency": 806, "weight": 10, "from_interface": "i4", "to_interface": "i0", "bidirectional": true}, {"bandwidth": 88825, "from_router": "a10_Dojima", "to_router": "a24_Hiroshima", "latency": 469, "weight": 100, "from_interface": "i5", "to_interface": "i0", "bidirectional": true}, {"bandwidth": 888252, "from_router": "a10_Dojima", "to_router": "a25_Kurashiki", "latency": 267, "weight": 10, "from_interface": "i6", "to_interface": "i0", "bidirectional": true}, {"bandwidth": 499999, "from_router": "a10_Dojima", "to_router": "a26_Sakyo", "latency": 890, "weight": 17, "from_interface": "i7", "to_interface": "i0", "bidirectional": true}, {"bandwidth": 88825, "from_router": "a21_Fujisawa", "to_router": "a22_Nara", "latency": 574, "weight": 100, "from_interface": "i2", "to_interface": "i1", "bidirectional": true}, {"bandwidth": 499999, "from_router": "a22_Nara", "to_router": "a26_Sakyo", "latency": 939, "weight": 17, "from_interface": "i2", "to_interface": "i1", "bidirectional": true}, {"bandwidth": 44412, "from_router": "a23_Fukuoka", "to_router": "a24_Hiroshima", "latency": 350, "weight": 200, "from_interface": "i1", "to_interface": "i1", "bidirectional": true}, {"bandwidth": 888252, "from_router": "a23_Fukuoka", "to_router": "a25_Kurashiki", "latency": 549, "weight": 10, "from_interface": "i2", "to_interface": "i1", "bidirectional": true}]}}